cerebrixos_trustmesh/__init__.py
cerebrixos_trustmesh/ziti_router_auto_enroll.py
cerebrixos_trustmesh-0.3.1.dist-info/METADATA
cerebrixos_trustmesh-0.3.1.dist-info/WHEEL
cerebrixos_trustmesh-0.3.1.dist-info/entry_points.txt
cerebrixos_trustmesh-0.3.1.dist-info/RECORD
