Metadata-Version: 2.4
Name: CerebrixOS-TrustMesh
Version: 0.3.1
Summary: Install CerebrixOS router to expose internal private services over zero-trust network
Author-email: CerebrixOS <vc@cerebrixos.com>
Classifier: Programming Language :: Python :: 3.6
Classifier: Programming Language :: Python :: 3.7
Classifier: Programming Language :: Python :: 3.8
Classifier: Programming Language :: Python :: 3.9
Classifier: Programming Language :: Python :: 3.10
Classifier: Programming Language :: Python :: 3.11
Classifier: Programming Language :: Python :: 3.12
Requires-Python: >=3.6
Requires-Dist: colorama>=0.4.6
Requires-Dist: distro>=1.9.0
Requires-Dist: jinja2>=3.0.3
Requires-Dist: packaging>=21.3
Requires-Dist: psutil>=6.1.1
Requires-Dist: pyinstaller>=4.10
Requires-Dist: pyjwt>=2.4.0
Requires-Dist: pylint-exit>=1.2.0
Requires-Dist: pylint>=2.12.0
Requires-Dist: pyyaml>=6.0.1
Requires-Dist: requests>=2.27.1
Requires-Dist: tqdm>=4.64.1
